README.md
pbz_heap.py
setup.py
pbz_heap.egg-info/PKG-INFO
pbz_heap.egg-info/SOURCES.txt
pbz_heap.egg-info/dependency_links.txt
pbz_heap.egg-info/top_level.txt