Metadata-Version: 2.1
Name: pbz-heap
Version: 0.0.1
Summary: Min and Max Heap implementation in Python.
Home-page: http://github.com/Pebaz/pbz-heap
Author: http://github.com/Pebaz
License: MIT
Platform: UNKNOWN
